{"data_non_statistical":false,"goal_meta_link":"https://unstats.un.org/sdgs/files/metadata-compilation/Metadata-Goal-8.pdf","goal_meta_link_text":"United Nations Sustainable Development Goals Metadata (PDF 231 KB)","graph_title":"Proporci\u00f3 d'ocupaci\u00f3 informal en el sector no agr\u00edcola, desglossada per sexe","graph_type":"line","indicator_number":"8.3.1","indicator_name":"Proporci\u00f3 d'ocupaci\u00f3 informal en el sector no agr\u00edcola, desglossada per sexe","indicator_sort_order":"08-03-01","published":true,"reporting_status":"notstarted","sdg_goal":"8","target_name":"Promoure pol\u00edtiques orientades al desenvolupament que donin suport a les activitats productives, la creaci\u00f3 d\u2019ocupaci\u00f3 digna, l\u2019emprenedoria, la creativitat i la innovaci\u00f3, i encoratjar la regularitzaci\u00f3 i el creixement de les microempreses i les petites i mitjanes empreses, a trav\u00e9s, entre d\u2019altres, de l\u2019acc\u00e9s a serveis financers.","target_id":"8.3","un_custodian_agency":"International Labour Organisation (ILO)","un_designated_tier":"2","page_content":"","national_metadata_update_url_text":"2021-04-05: see changes on GitHub","national_metadata_update_url":"https://github.com/Agenda2030-BCN/bcn2030-data/commit/9fcadae71095f1c1f814970bd9e58b9f848551c8","national_data_update_url_text":"2021-04-05: see changes on GitHub","national_data_update_url":"https://github.com/Agenda2030-BCN/bcn2030-data/commit/9fcadae71095f1c1f814970bd9e58b9f848551c8","indicator":"8.3.1"}